pytrackereulerian/__init__.py
pytrackereulerian/main.py
pytrackereulerian/url_generator/__init__.py
pytrackereulerian/url_generator/afiliacion.py
pytrackereulerian/url_generator/bing_ads.py
pytrackereulerian/url_generator/colaboracion.py
pytrackereulerian/url_generator/comparador.py
pytrackereulerian/url_generator/core.py
pytrackereulerian/url_generator/display.py
pytrackereulerian/url_generator/emailing.py
pytrackereulerian/url_generator/google_ads.py
pytrackereulerian/url_generator/social.py
pytrackereulerian-1.1.0.dist-info/LICENSE
pytrackereulerian-1.1.0.dist-info/METADATA
pytrackereulerian-1.1.0.dist-info/WHEEL
pytrackereulerian-1.1.0.dist-info/entry_points.txt
pytrackereulerian-1.1.0.dist-info/top_level.txt
pytrackereulerian-1.1.0.dist-info/RECORD
