Metadata-Version: 2.1
Name: pytrackereulerian
Version: 1.1.0
Summary: Herramienta para la generación de URLs de tracking.
Home-page: https://github.com/abutrag/pytrackereulerian
Author: abutrag
Author-email: a.butragueno@eulerian.com
Classifier: Programming Language :: Python :: 3
Classifier: License :: OSI Approved :: MIT License
Classifier: Operating System :: OS Independent
Requires-Python: >=3.7
License-File: LICENSE
